rtl/dataMemory.v
module dMem	#(parameter addrWidth = 32, ramHeight = 2048, ramWidth = 32)	
			(input clk, rst_, memRd, memWrt,
			input [addrWidth - 1: 0] addr,
			input [ramWidth - 1: 0] dataIn,
			output [ramWidth - 1: 0] dataOut);

reg [ramWidth - 1 : 0] memory [ramHeight - 1: 0];

assign dataOut = memRd ? memory[addr] : 32'dx;

always @ (posedge clk or negedge rst_) begin
	if(!rst_) begin
		for(integer i = 0; i < ramHeight; i++)
			memory[i] = 32'd0;
	end
	else if(memWrt) begin
		memory[addr] = dataIn;
	end
end

endmodule

rtl/ALU.v
module alu	(input [3:0] opcode,
			input [31:0] A, B,
			output carry, zero,
			output reg [31:0] Y
			);

reg adderCarryOut;

localparam	ADD = 4'b0000, SUB = 4'b0001, SLL = 4'b0010,
			XOR = 4'b0011, SRL = 4'b0100, SRA = 4'b0101,
			OR = 4'b0110, AND = 4'b0111, SLTU = 4'b1000,
			BNE = 4'b1001, BEQ = 4'b1010, LUI = 4'b1011;

always @ (*) begin
	case(opcode)
		ADD: {adderCarryOut, Y} = A + B;
		SUB: Y = A - B;
		SLL: Y = A << B;
		XOR: Y = A ^ B;
		SRL: Y = A >> B;
		SRA: Y = {A[31], 31'd0} | A>>B;
		OR:  Y = A | B;
		AND: Y = A & B;
		SLTU: Y = (A < B) ? 1'b1 : 1'b0;
		BNE: Y = (A != B) ? 1'b0 : 1'b1;
		BEQ: Y = (A == B) ? 1'b1 : 1'b0;
		LUI: Y = {B, {12{1'b0}}};
		default: Y = 4'd0;
	endcase
end

assign carry = (opcode == ADD && adderCarryOut == 1) ? 1'b1 :
			   (opcode == BEQ && Y == 1) ? 1'b1 :
			   1'b0;

assign zero = (Y == 32'd0) ? 1'b1 : 1'b0;

endmodule

immediateGenerator.v
`timescale 1ns / 1ps

module immediateGen(input [31:0] instruction,
		    output [31:0] immediate);

localparam iType = 7'b0010011, lType = 7'b0000011, sType = 7'b0100011, 
	   sbType = 7'b1100011, uType = 7'b0110111, ujType = 7'b1101111;

//Going with I - Type instruction as default

always @ (instruction) begin
	case(instruction[6:0])
		iType | lType: immediate = {{20{instruction[31]}}, instruction[31:20]};
		sType: immediate = {{20{instruction[31]}}, instruction[31:25], instruction[11:7]};
		sbType: immediate = {{20{instruction[31]}}, instruction[7], instruction[30:25], instruction[11:8], 1'b0};
		uType: immediate = {instruction[31:12],{12{1'b0}}};
		ujType: immediate = {{12{instruction[31]}}, instruction[19:12], instruction[20], instruction[30:21], 1'b0};
		default: immediate = {{20{instruction[31]}}, instruction[31:20]};
	endcase
end

endmodule

rtl/registers.v
module registers    (input clk, rst_, wrtEn,
                    input [4:0] rdReg1, rdReg2, wrtReg,
                    input [31:0] wrtData, 
                    output [31:0] rdData1, rdData2
                    );

reg [31:0] regFile [31:0];

assign rdData1 = regFile[rdReg1];
assign rdData2 = regFile[rdReg2];

always @ (posedge clk or negedge rst_) begin
    if(!rst_) begin
        for(integer i = 0; i < 32; i = i + 1)
            regFile[i] = 0;
    end
    else if(wrtEn)
        regFile[wrtReg] = wrtData;
    regFile[0] = 0; //Reg 0 is a constant.
end

endmodule

rtl/aluController.v
module aluController    (input funct7,
                        input [1:0] aluOp,
                        input [2:0] funct3,
                        input [6:0] instrnOpcode,
                        output reg [3:0] aluControl
                        );
                     
localparam memoryInst = 2'b00, bitwiseOrShift = 2'b01,
           branch = 2'b10, upperImmediate = 2'b11;

/*  aluControl determines which operation takes place at the ALU
    ADD = 4'b0000    SUB = 4'b0001    SLL = 4'b0010    XOR = 4'b0011  
    SRL = 4'b0100    SRA = 4'b0101    OR = 4'b0110     AND = 4'b0111
    SLT = 4'b1000 where SLT is unsigned 
    and please note that just for I type shifts - The MSB - 1 bit has to be 1 for SRAI which would be represented by funct7
*/

always @ (*) begin
    case(aluOp)
        memoryInst: 
            aluControl = 4'b0000;
        bitwiseOrShift:begin
            if(funct7 && instrnOpcode == 7'b0110011)
                aluControl = (funct3 == 3'b101) ? 4'b0101 : 4'b0001;
            else if(funct7 && funct3 == 3'b101 && instrnOpcode == 7'b0010011)
                aluControl = 4'b0101;
			else begin
                case(funct3)
				    3'b000: aluControl = 4'b0000;
					3'b001: aluControl = 4'b0010;
					3'b010: aluControl = 4'b1000;
					3'b100: aluControl = 4'b0011;
					3'b101: aluControl = 4'b0100;
					3'b110: aluControl = 4'b0110;
					3'b111: aluControl = 4'b0111;
					default: aluControl = 4'b0000;
				endcase
			end                    
		end
        branch:begin
            if(funct3 == 000)
                aluControl = 4'b1010;
            else
                aluControl = 4'b1001;
		end
        upperImmediate:
            aluControl = 4'b1011;
    endcase
end

endmodule

controlUnit.v
`timescale 1ns / 1ps

module controller (input [31:0] instruction,
		   output aluSrc, branch, jump, memRd, memWrt, regWrt,
		   output [1:0] aluOp, memToreg);

/* iType instructions consists of bitwise operations, loads and JALR.
   Each sub type has its own OPCODE but the general iType instruction encoding is consistently followed.
   To simplify ISA implementation, introducing L type for loads and restricting implementation to just JAL (uj-type).
*/

// aluSrc (0, 1) = (rdData2, immediate), memToReg (0, 1, 2) = (ALU Output, Load Data Out, PC+4)

localparam iType = 7'b0010011, lType = 7'b0000011, rType = 7'b0110011, sType = 7'b0100011, 
	   sbType = 7'b1100011, uType = 7'b0110111, ujType = 7'b1101111;

always @ (instruction) begin
	case(instruction[6:0])
		iType:	begin
				aluSrc = 1'b1;
				branch = 1'b0;
				jump = 1'b0;
				memRd = 1'b0;
				memWrt = 1'b0;
				regWrt = 1'b1;
				aluOp = 2'b01;
				memToReg = 2'b00;
			end
		lType:	begin
				aluSrc = 1'b1;
				branch = 1'b0;
				jump = 1'b0;
				memRd = 1'b1;
				
				memWrt = 1'b0;
				regWrt = 1'b1;
				aluOp = 2'b00;
				memToReg = 2'b01;
			end
		rType:	begin
				aluSrc = 1'b0;
				branch = 1'b0;
				jump = 1'b0;
				memRd = 1'b0;
				memWrt = 1'b0;
				regWrt = 1'b1;
				aluOp = 2'b01;
				memToReg = 2'b01;
			end
		
		sType:	begin
				aluSrc = 1'b1;
				branch = 1'b0;
				jump = 1'b0;
				memRd = 1'b0;
				memWrt = 1'b1;
				regWrt = 1'b0;
				aluOp = 2'b00;
				memToReg = 2'bxx;
			end
		sbType:	begin
				aluSrc = 1'b0;
				branch = 1'b1;
				jump = 1'b0;
				memRd = 1'b0;
				memWrt = 1'b0;
				regWrt = 1'b0;
				aluOp = 2'b10;
				memToReg = 2'bxx;
			end
		uType:	begin
				aluSrc = 1'b1;
				branch = 1'b0;
				jump = 1'b0;
				memRd = 1'b0;
				memWrt = 1'b0;
				regWrt = 1'b1;
				aluOp = 2'b11;
				memToReg = 2'b00;
			end
		ujType:	begin
				aluSrc = 1'b1;
				branch = 1'b0;
				jump = 1'b1;
				memRd = 1'b0;
				memWrt = 1'b0;
				regWrt = 1'b1;
				aluOp = 2'bxx;
				memToReg = 2'b10;
			end
	endcase
end

endmodule

rtl/instrnMemory.v
module iMem	(input [31:0] addr,
			output [31:0] instrn);

//32 bits may have been allcoated for the address location, but the totatl no. of available locations are 128.

reg [7:0] memory [127:0];

// 1 Kb instruction memory - upto 32 unique instructions, can be easily scaled depending on program requirements

initial begin
	for(integer i = 0; i < 128; i = i + 1)
		memory[i] = 32'd0;
	
	/*In risc v, memory increments as PC + 4. This indicates to us that
	it is byte addressable hence each location in the ROM is a byte wide.
	On the other hand for the data memory, since, I am implementing only
	LW and SW for mem movement operations, I designed the data memory to
	be strictly word addressable.*/

	// ... enter program here ...

	//When reset is low each reg is written with a zero;
	// //Demo Program 1: This program tests I, R, SB and UJ types.

	// //INSTR1:	ADDI X01, X01, 21
	// memory[0]  = 8'b10010011;
	// memory[1]  = 8'b10000000;
	// memory[2]  = 8'b01010000;
	// memory[3]  = 8'b00000001;

	// //INSTR2:	ADDI X02, X02, 12
	// memory[4]  = 8'b00010011;
	// memory[5]  = 8'b00000001;
	// memory[6]  = 8'b11000001;
	// memory[7]  = 8'b00000000;

	// //			ADDI X04, X04, 1D
	// memory[8]  = 8'b00010011;
	// memory[9]  = 8'b00000010;
	// memory[10] = 8'b11010010;
	// memory[11] = 8'b00000001;

	// //			OR X03, X02, X01
	// memory[12] = 8'b10110011;
	// memory[13] = 8'b01100001;
	// memory[14] = 8'b00010001;
	// memory[15] = 8'b00000000;

	// //			ADDI X03, X03, 1
	// memory[16] = 8'b10010011;
	// memory[17] = 8'b10000001;
	// memory[18] = 8'b00010001;
	// memory[19] = 8'b00000000;

	// //			BEQ X03, X04, INSTR2
	// memory[20] = 8'b11100011;
	// memory[21] = 8'b10001000;
	// memory[22] = 8'b01000001;
	// memory[23] = 8'b11111110;

	// //			JAL  X5 INSTR1
	// memory[24] = 8'b11101111;
	// memory[25] = 8'b11110010;
	// memory[26] = 8'b10011111;
	// memory[27] = 8'b11111110;

	//Demo program 2: This program tests memory movement instructions L and S types.

	//				ADDI X07, X07, 1500
	memory[0]  = 8'b10010011;
	memory[1]  = 8'b10000011;
	memory[2]  = 8'b11000011;
	memory[3]  = 8'b01011101;

	//				ADDI X06. X06, 1200
	memory[4]  = 8'b00010011;
	memory[5]  = 8'b00000011;
	memory[6]  = 8'b00000011;
	memory[7]  = 8'b01001011;

	//				SW X07, 23(X06)
	memory[8]  = 8'b10100011;
	memory[9]  = 8'b00101011;
	memory[10] = 8'b01110011;
	memory[11] = 8'b00000000;

	//				ADDI X08, X08, 1223
	memory[12] = 8'b00010011;
	memory[13] = 8'b00000100;
	memory[14] = 8'b01110100;
	memory[15] = 8'b01001100;

	//				LW X09, 0(X08)
	memory[16] = 8'b10000011;
	memory[17] = 8'b00100100;
	memory[18] = 8'b00000100;
	memory[19] = 8'b00000000;

	//				SUB X09, X09, X00
	memory[20] = 8'b10110011;
	memory[21] = 8'b10000100;
	memory[22] = 8'b00000100;
	memory[23] = 8'b00000000;

end

assign instrn = {memory[addr + 3], memory[addr + 2], memory[addr + 1], memory[addr]};

endmodule

rtl/runningCore.v
`timescale 1ns/1ps

module riscVCore	(input clk, rst_);

//wire			mClk;			    //Output of clocking Wizard IP at 80 MHz
//wire			locked;             //Used to assure IP based clock is ready
reg 	[31:0]	pc;				    //Instrn. address at hand
wire 	[31:0]	pcNext;			    //Instrn. address to be latched next

wire	[31:0]	instruction;	    //Data o/p received from instruction memory

wire			aluSrc;			    //MUX 0 - Regular (Read Data 2), 1 - Sign extended immediate value
wire			branch;			    //Branch Flag for SB-Type
wire			jump;			    //Jump Flag for JAL (UJ-Type)
wire			memRead;		    //Loading into Data Memory
wire			memWrite;		    //Storing into Data Memory 
wire			regWrite;		    //Writeback into Register File
wire    [1:0]   memToReg;           //MUX 0 - ALU output, 1 - Memory to Register, 2 PC + 4 Value
wire	[1:0]	aluOp;			    //Determines ALU operation category

wire	[31:0]	readData1;	        //Register 1 Read Data
wire	[31:0]	readData2;	        //Register 2 Read Data
wire	[4:0]	readReg1;		    //Read Register 1
wire	[4:0]	readReg2;		    //Read Register 2
wire	[4:0]	writeReg;		    //Write Register
wire	[31:0]	writeData;	        //Write Data

wire	[31:0]	immGenOut;	        //Sign extended o/p of immediate

wire	[3:0]	aluControl;	        //ALU operation taking place now

wire	[31:0]	dataMemOut;

wire			C;				    //ALU Carry Flag
wire 	        Z;                  //ALU Zero Flag
wire	[31:0]	Y;                  //ALU Result
wire	[31:0]	A;                  //ALU Operand 1
wire	[31:0]	B;                  //ALU Operand 2

wire            branchCondition;    //Use zero or Carry for BNE or BEQ 
wire			yesBranch;		    //Branch condition is met
wire            assertBranchOrJump; //Check whether jump or branch condition is met
wire            addrSel;            //PC+4 or jump/branch address

// ==================== programCounter.v ====================
assign branchCondition =    (aluControl === 4'b1001 && Z == 1) ? 1 :
                            (aluControl === 4'b1010 && C == 1) ? 1 : 0;
assign yesBranch = branch & branchCondition;
assign assertBranchOrJump = yesBranch || jump;
assign addrSel = (assertBranchOrJump) ? 1 : 0;
assign pcNext = addrSel ? (pc + immGenOut) : (pc + 4);

always @ (posedge clk)
    pc <= !rst_ ? 0 : pcNext;

// ==================== instrnMemory.v ====================
iMem IMEM0	(
			.addr(pc),
			.instrn(instruction)
			);

// ==================== mainController.v ====================
controller MC0  (
                .instruction(instruction),
                .aluSrc(aluSrc),
                .jump(jump),
                .branch(branch),
                .memRd(memRead),
                .memToReg(memToReg),
                .memWrt(memWrite),
                .regWrt(regWrite),
                .aluOp(aluOp)
                );

// ==================== aluController.v ====================
aluController AC0	(
					.funct7(instruction[30]),
                    .aluOp(aluOp),
                    .funct3(instruction[14:12]),
                    .instrnOpcode(instruction[6:0]),
                    .aluControl(aluControl)
                    );

// ==================== registers.v ====================
assign writeData =  (memToReg == 2'b00) ? Y :
                    ((memToReg == 2'b01) ? dataMemOut : (pc + 4));

assign readReg1 = instruction[19:15];
assign readReg2 = instruction[24:20];
assign writeReg = instruction[11:7];

registers RF0   (
				.clk(clk),
                .rst_(rst_),
                .wrtEn(regWrite),
                .rdReg1(readReg1),
                .rdReg2(readReg2),
                .wrtReg(writeReg),
                .wrtData(writeData), 
                .rdData1(readData1),
                .rdData2(readData2)
                );

// ==================== immediateGenerator.v ====================
immediateGen IG0	(
					.instruction(instruction),
                    .immediate(immGenOut)
                    );

// ==================== ALU.v ====================
assign A = readData1;
assign B = aluSrc ? immGenOut : readData2;

alu ALU0    (
			.opcode(aluControl),
            .A(A),
            .B(B),
            .carry(C),
            .zero(Z),
            .Y(Y)
            );

// ==================== dataMemory.v ====================
dMem DMEM0	(
			.clk(clk),
			.rst_(rst_),
			.memRd(memRead),
			.memWrt(memWrite),
			.addr(Y),
			.dataIn(readData2),
			.dataOut(dataMemOut)
			);

/*// Follow bellow instantiation for FPGA implementation. These IPs were instantiated through Xillinx Vivado

// // ==================== BRAM MODULE ====================
// blk_mem_gen_0 DMEM   (
                        .clka(mClk),
//                      .ena(memRead),
//                      .wea(memWrite),
//                      .addra(Y),
//                      .dina(readData2),
//                      .douta(dataMemOut)
//                      );

// // ==================== CLOCK MODULE ====================
// clk_wiz_0 SYSCLK (
                    .clk_out1(mClk),
//                  .reset(rst),
//                  .locked(locked),
//                  .clk_in1(clk)
//                  );*/
    
endmodule

sim/mainTestBench.v
module mainTestBench;

reg clk = 0, rst_;

riscVCore DUT (clk, rst_);

always
	#5 clk = ~clk;

initial begin
	
	$dumpfile("mainTestTrace.vcd");
	$dumpvars(0, mainTestBench);

	rst_ = 0; #10;
	rst_ = 1; #90;

	$finish;

end

endmodule

mainTestTrace.vcd
$date
	Wed Oct 25 01:27:39 2023
$end
$version
	Icarus Verilog
$end
$timescale
	1ps
$end
$scope module mainTestBench $end
$var reg 1 ! clk $end
$var reg 1 " rst_ $end
$scope module DUT $end
$var wire 32 # A [31:0] $end
$var wire 1 $ assertBranchOrJump $end
$var wire 1 ! clk $end
$var wire 1 " rst_ $end
$var wire 1 % yesBranch $end
$var wire 5 & writeReg [4:0] $end
$var wire 32 ' writeData [31:0] $end
$var wire 1 ( regWrite $end
$var wire 5 ) readReg2 [4:0] $end
$var wire 5 * readReg1 [4:0] $end
$var wire 32 + readData2 [31:0] $end
$var wire 32 , readData1 [31:0] $end
$var wire 32 - pcNext [31:0] $end
$var wire 1 . memWrite $end
$var wire 2 / memToReg [1:0] $end
$var wire 1 0 memRead $end
$var wire 1 1 jump $end
$var wire 32 2 instruction [31:0] $end
$var wire 32 3 immGenOut [31:0] $end
$var wire 32 4 dataMemOut [31:0] $end
$var wire 1 5 branchCondition $end
$var wire 1 6 branch $end
$var wire 1 7 aluSrc $end
$var wire 2 8 aluOp [1:0] $end
$var wire 4 9 aluControl [3:0] $end
$var wire 1 : addrSel $end
$var wire 1 ; Z $end
$var wire 32 < Y [31:0] $end
$var wire 1 = C $end
$var wire 32 > B [31:0] $end
$var reg 32 ? pc [31:0] $end
$scope module AC0 $end
$var wire 3 @ funct3 [2:0] $end
$var wire 1 A funct7 $end
$var wire 7 B instrnOpcode [6:0] $end
$var wire 2 C aluOp [1:0] $end
$var reg 4 D aluControl [3:0] $end
$upscope $end
$scope module ALU0 $end
$var wire 32 E A [31:0] $end
$var wire 32 F B [31:0] $end
$var wire 4 G opcode [3:0] $end
$var wire 1 ; zero $end
$var wire 1 = carry $end
$var reg 32 H Y [31:0] $end
$var reg 1 I adderCarryOut $end
$upscope $end
$scope module DMEM0 $end
$var wire 32 J addr [31:0] $end
$var wire 1 ! clk $end
$var wire 1 " rst_ $end
$var wire 1 . memWrt $end
$var wire 1 0 memRd $end
$var wire 32 K dataOut [31:0] $end
$var wire 32 L dataIn [31:0] $end
$scope begin $ivl_for_loop0 $end
$var integer 32 M i [31:0] $end
$upscope $end
$upscope $end
$scope module IG0 $end
$var wire 32 N instruction [31:0] $end
$var reg 32 O immediate [31:0] $end
$upscope $end
$scope module IMEM0 $end
$var wire 32 P addr [31:0] $end
$var wire 32 Q instrn [31:0] $end
$scope begin $ivl_for_loop1 $end
$var integer 32 R i [31:0] $end
$upscope $end
$upscope $end
$scope module MC0 $end
$var wire 32 S instruction [31:0] $end
$var reg 2 T aluOp [1:0] $end
$var reg 1 7 aluSrc $end
$var reg 1 6 branch $end
$var reg 1 1 jump $end
$var reg 1 0 memRd $end
$var reg 2 U memToReg [1:0] $end
$var reg 1 . memWrt $end
$var reg 1 ( regWrt $end
$upscope $end
$scope module RF0 $end
$var wire 1 ! clk $end
$var wire 32 V rdData1 [31:0] $end
$var wire 32 W rdData2 [31:0] $end
$var wire 5 X rdReg1 [4:0] $end
$var wire 5 Y rdReg2 [4:0] $end
$var wire 1 " rst_ $end
$var wire 32 Z wrtData [31:0] $end
$var wire 1 ( wrtEn $end
$var wire 5 [ wrtReg [4:0] $end
$scope begin $ivl_for_loop2 $end
$var integer 32 \ i [31:0] $end
$upscope $end
$upscope $end
$upscope $end
$upscope $end
$enddefinitions $end
#0
$dumpvars
b100000 \
bx [
bx Z
bx Y
bx X
bx W
bx V
bx U
bx T
bx S
b10000000 R
bx Q
bx P
bx O
bx N
b100000000000 M
bx L
bx K
bx J
xI
bx H
bx G
bx F
bx E
bx D
bx C
bx B
xA
bx @
bx ?
bx >
x=
bx <
x;
x:
bx 9
bx 8
x7
x6
05
bx 4
bx 3
bx 2
x1
x0
bx /
x.
bx -
bx ,
bx +
bx *
bx )
x(
bx '
bx &
0%
x$
bx #
0"
0!
$end
#5000
0=
0:
0;
b10111011100 '
b10111011100 Z
0I
b10111011100 <
b10111011100 H
b10111011100 J
b0 9
b0 D
b0 G
0$
b10111011100 >
b10111011100 F
b100 -
1A
b0 +
b0 L
b0 W
b11100 )
b11100 Y
b0 #
b0 E
b0 ,
b0 V
b111 *
b111 X
b0 @
b111 &
b111 [
b10011 B
b10111011100 3
b10111011100 O
b0 /
b0 U
b1 8
b1 C
b1 T
1(
0.
00
01
06
17
b1011101110000111000001110010011 2
b1011101110000111000001110010011 N
b1011101110000111000001110010011 Q
b1011101110000111000001110010011 S
b0 ?
b0 P
b100000000000 M
b100000 \
1!
#10000
0!
1"
#15000
b10010110000 >
b10010110000 F
b1000 -
b10000 )
b10000 Y
b110 *
b110 X
b110 &
b110 [
b10010110000 3
b10010110000 O
b1001011000000110000001100010011 2
b1001011000000110000001100010011 N
b1001011000000110000001100010011 Q
b1001011000000110000001100010011 S
b100 ?
b100 P
b10010110000 '
b10010110000 Z
b10010110000 <
b10010110000 H
b10010110000 J
b0 #
b0 E
b0 ,
b0 V
1!
#20000
0!
#25000
b10111 >
b10111 F
b1100 -
0A
b10111011100 +
b10111011100 L
b10111011100 W
b111 )
b111 Y
b10 @
b10111 &
b10111 [
b100011 B
b10111 3
b10111 O
bx /
bx U
b0 8
b0 C
b0 T
0(
1.
b11100110010101110100011 2
b11100110010101110100011 N
b11100110010101110100011 Q
b11100110010101110100011 S
b1000 ?
b1000 P
bx '
bx Z
b10011000111 <
b10011000111 H
b10011000111 J
b10010110000 #
b10010110000 E
b10010110000 ,
b10010110000 V
1!
#30000
0!
#35000
b10011000111 '
b10011000111 Z
b10011000111 >
b10011000111 F
b10000 -
1A
b0 #
b0 E
b0 ,
b0 V
b1000 *
b1000 X
b0 @
b1000 &
b1000 [
b10011 B
b0 /
b0 U
b1 8
b1 C
b1 T
1(
0.
b10011000111 3
b10011000111 O
b1001100011101000000010000010011 2
b1001100011101000000010000010011 N
b1001100011101000000010000010011 Q
b1001100011101000000010000010011 S
b1100 ?
b1100 P
1!
#40000
0!
#45000
b10111011100 4
b10111011100 K
b0 >
b0 F
b10100 -
0A
b0 +
b0 L
b0 W
b0 )
b0 Y
b10 @
b1001 &
b1001 [
b11 B
b0 3
b0 O
b1 /
b1 U
b0 8
b0 C
b0 T
10
b1000010010010000011 2
b1000010010010000011 N
b1000010010010000011 Q
b1000010010010000011 S
b10000 ?
b10000 P
b10111011100 '
b10111011100 Z
b10011000111 <
b10011000111 H
b10011000111 J
b10011000111 #
b10011000111 E
b10011000111 ,
b10011000111 V
1!
#50000
0!
#55000
b10111011100 <
b10111011100 H
b10111011100 J
b10111011100 '
b10111011100 Z
bx 4
bx K
b11000 -
b10111011100 #
b10111011100 E
b10111011100 ,
b10111011100 V
b1001 *
b1001 X
b0 @
b110011 B
b0 /
b0 U
b1 8
b1 C
b1 T
00
07
b1001000010010110011 2
b1001000010010110011 N
b1001000010010110011 Q
b1001000010010110011 S
b10100 ?
b10100 P
1!
#60000
0!
#65000
1;
b0 '
b0 Z
b0 <
b0 H
b0 J
b11100 -
b0 #
b0 E
b0 ,
b0 V
b0 *
b0 X
b0 &
b0 [
b0 B
b0 2
b0 N
b0 Q
b0 S
b11000 ?
b11000 P
1!
#70000
0!
#75000
b100000 -
b11100 ?
b11100 P
1!
#80000
0!
#85000
b100100 -
b100000 ?
b100000 P
1!
#90000
0!
#95000
b101000 -
b100100 ?
b100100 P
1!
